AUTHORS.rst
COPYING
MANIFEST.in
README.rst
setup.cfg
setup.py
doc/Makefile
doc/README
doc/about.rst
doc/conf.py
doc/data_transforms.rst
doc/documentation.rst
doc/faq.rst
doc/index.rst
doc/install.rst
doc/make.bat
doc/model_selection.rst
doc/preface.rst
doc/presentations.rst
doc/related_projects.rst
doc/supervised_learning.rst
doc/support.rst
doc/tune_toc.rst
doc/unsupervised_learning.rst
doc/user_guide.rst
doc/whats_new.rst
doc/datasets/covtype.rst
doc/datasets/index.rst
doc/datasets/labeled_faces.rst
doc/datasets/labeled_faces_fixture.py
doc/datasets/mldata.rst
doc/datasets/mldata_fixture.py
doc/datasets/olivetti_faces.rst
doc/datasets/rcv1.rst
doc/datasets/rcv1_fixture.py
doc/datasets/twenty_newsgroups.rst
doc/datasets/twenty_newsgroups_fixture.py
doc/developers/contributing.rst
doc/developers/debugging.rst
doc/developers/index.rst
doc/developers/maintainer.rst
doc/developers/performance.rst
doc/developers/utilities.rst
doc/images/cds-logo.png
doc/images/inria-logo.jpg
doc/images/iris.pdf
doc/images/iris.svg
doc/images/last_digit.png
doc/images/lda_model_graph.png
doc/images/ml_map.png
doc/images/no_image.png
doc/images/plot_digits_classification.png
doc/images/plot_face_recognition_1.png
doc/images/plot_face_recognition_2.png
doc/images/rbm_graph.png
doc/images/scikit-learn-logo-notext.png
doc/includes/big_toc_css.rst
doc/includes/bigger_toc_css.rst
doc/logos/favicon.ico
doc/logos/identity.pdf
doc/logos/scikit-learn-logo-notext.png
doc/logos/scikit-learn-logo-small.png
doc/logos/scikit-learn-logo-thumb.png
doc/logos/scikit-learn-logo.bmp
doc/logos/scikit-learn-logo.png
doc/logos/scikit-learn-logo.svg
doc/modules/biclustering.rst
doc/modules/calibration.rst
doc/modules/classes.rst
doc/modules/clustering.rst
doc/modules/computational_performance.rst
doc/modules/covariance.rst
doc/modules/cross_decomposition.rst
doc/modules/cross_validation.rst
doc/modules/decomposition.rst
doc/modules/density.rst
doc/modules/dp-derivation.rst
doc/modules/ensemble.rst
scikit_learn_runnr.egg-info/PKG-INFO
scikit_learn_runnr.egg-info/SOURCES.txt
scikit_learn_runnr.egg-info/dependency_links.txt
scikit_learn_runnr.egg-info/not-zip-safe
scikit_learn_runnr.egg-info/top_level.txt
