Metadata-Version: 1.1
Name: scikit-learn-runnr
Version: 0.18.dev1
Summary: A set of python modules for machine learning and data mining
Home-page: http://scikit-learn.org
Author: Andreas Mueller
Author-email: amueller@ais.uni-bonn.de
License: new BSD
Download-URL: http://sourceforge.net/projects/scikit-learn/files/
Platform: UNKNOWN
Classifier: Intended Audience :: Science/Research
Classifier: Intended Audience :: Developers
Classifier: License :: OSI Approved
Classifier: Programming Language :: C
Classifier: Programming Language :: Python
Classifier: Topic :: Software Development
Classifier: Topic :: Scientific/Engineering
Classifier: Operating System :: Microsoft :: Windows
Classifier: Operating System :: POSIX
Classifier: Operating System :: Unix
Classifier: Operating System :: MacOS
Classifier: Programming Language :: Python :: 2
Classifier: Programming Language :: Python :: 2.6
Classifier: Programming Language :: Python :: 2.7
Classifier: Programming Language :: Python :: 3
Classifier: Programming Language :: Python :: 3.3
Classifier: Programming Language :: Python :: 3.4
